__init__.py
bdt_scale.py
cmb_ck.py
cs_reader.py
extractor.py
extset.py
mc_reader.py
model_manager.py
normalizer.py
np_reader.py
rk_model.py
rkex_model.py
scales.py
extractor_data/__init__.py
extractor_data/bdt_eff/__init__.py
extractor_data/config/__init__.py
extractor_data/config/v1.toml
extractor_data/config/v2.toml
extractor_data/config/v3.toml
extractor_data/config/v4.toml
extractor_data/config/v5.toml
extractor_data/config/v6.toml
extractor_data/config/v7.toml
extractor_data/npr_data/__init__.py
extractor_data/npr_data/v65_v63_v24/eff_ee.json
extractor_data/npr_data/v65_v63_v24/eff_mm.json
extractor_data/npr_data/v65_v63_v24/sta_ee.json
extractor_data/npr_data/v65_v63_v24/sta_mm.json
extractor_data/npr_data/v65_v63_v24/sys_ee.json
extractor_data/npr_data/v65_v63_v24/sys_mm.json
extractor_data/npr_data/v65_v63_v24/yld_ee.json
extractor_data/npr_data/v65_v63_v24/yld_mm.json
extractor_data/npr_data/v65_v81_v24/eff.json
extractor_data/npr_data/v65_v81_v24/sta.json
extractor_data/npr_data/v65_v81_v24/sys.json
extractor_data/npr_data/v65_v81_v24/yld.json
extractor_data/rare_sf/__init__.py
extractor_data/rare_sf/v1/eff_real.json
extractor_data/rare_sf/v1/fr_bf.json
extractor_data/rare_sf/v2/eff_real.json
extractor_data/rare_sf/v2/fr_bf.json
extractor_data/rare_sf/v3/eff_real.json
extractor_data/rare_sf/v3/fr_bf.json
extractor_data/rare_sf/v4/eff_real.json
extractor_data/rare_sf/v4/fr_bf.json
extractor_data/rare_sf/v5/eff_real.json
extractor_data/rare_sf/v5/fr_bf.json
extractor_data/rare_sf/v6/eff_real.json
extractor_data/rare_sf/v6/fr_bf.json
extractor_data/rare_sf/v7/eff_real.json
extractor_data/rare_sf/v7/fr_bf.json
extractor_data/sb_fits/__init__.py
extractor_data/sb_fits/v1/2017_ETOS.json
extractor_data/sb_fits/v1/2017_GTIS.json
extractor_data/sb_fits/v1/2017_MTOS.json
extractor_data/sb_fits/v1/2018_ETOS.json
extractor_data/sb_fits/v1/2018_GTIS.json
extractor_data/sb_fits/v1/2018_MTOS.json
extractor_data/sb_fits/v1/all_ETOS.json
rk_extractor-1.1.6.dist-info/METADATA
rk_extractor-1.1.6.dist-info/WHEEL
rk_extractor-1.1.6.dist-info/top_level.txt
rk_extractor-1.1.6.dist-info/RECORD
