Metadata-Version: 2.1
Name: rk_extractor
Version: 1.1.6
Summary: Used to extract RK from simultaneous fits
Requires-Dist: numpy
Requires-Dist: toml
Requires-Dist: matplotlib
Requires-Dist: logzero
Requires-Dist: attrs
Requires-Dist: jacobi
Requires-Dist: scikit-learn ==1.2.2
Requires-Dist: rx-prec-accepance
Requires-Dist: rk-hadmisid-study >=0.0.6
Requires-Dist: rx-scripts >=0.2.2
Requires-Dist: rx-tools >=0.1.4
Requires-Dist: rx-combinatorial >=0.0.1
Requires-Dist: rx-hqm >=0.0.1
Requires-Dist: rx-phsp-cmb
Requires-Dist: rx-selection
Requires-Dist: zfit >=0.14.0
Requires-Dist: scipy
Requires-Dist: pandas
Requires-Dist: nlopt
